py_config_runner/__init__.py
py_config_runner/__main__.py
py_config_runner/config_utils.py
py_config_runner/deprecated.py
py_config_runner/runner.py
py_config_runner/utils.py
py_config_runner-0.3.2.dist-info/LICENSE
py_config_runner-0.3.2.dist-info/METADATA
py_config_runner-0.3.2.dist-info/WHEEL
py_config_runner-0.3.2.dist-info/entry_points.txt
py_config_runner-0.3.2.dist-info/top_level.txt
py_config_runner-0.3.2.dist-info/RECORD
