Metadata-Version: 2.1
Name: py-config-runner
Version: 0.3.2
Summary: Python configuration file and command line executable to run a script with
Home-page: https://github.com/vfdev-5/py_config_runner
Author: vfdev-5
Author-email: vfdev.5@gmail.com
License: UNKNOWN
Platform: UNKNOWN
Requires-Dist: click
Requires-Dist: pydantic
Provides-Extra: tests
Requires-Dist: pytest ; extra == 'tests'
Requires-Dist: pytest-cov ; extra == 'tests'
